xh_cache/CacheTool.py
xh_cache/__init__.py
xh_file_utils/FileUtils.py
xh_file_utils/__init__.py
xh_functional/FunctionalUtils.py
xh_functional/__init__.py
xh_ini_modifier/InitModifier.py
xh_ini_modifier/__init__.py
xh_serializable/__init__.py
xh_serializable/utils.py
xh_time_utils/__init__.py
xh_time_utils/utils.py
xh_utils_apache_log/ApacheLog.py
xh_utils_apache_log/__init__.py
xh_utils_file_changes/FileChanges.py
xh_utils_file_changes/__init__.py
xh_utils_ip/IpHostFinder.py
xh_utils_ip/IpTools.py
xh_utils_ip/__init__.py
xh_utils_progress/ProgressPinger.py
xh_utils_progress/__init__.py
xh_utils_script_file_writer/__init__.py
xh_utils_script_file_writer/script_writer.py
xh_utils_string/StringUtils.py
xh_utils_string/__init__.py
pyXhUtils-1.7.8.dist-info/LICENSE.txt
pyXhUtils-1.7.8.dist-info/METADATA
pyXhUtils-1.7.8.dist-info/WHEEL
pyXhUtils-1.7.8.dist-info/top_level.txt
pyXhUtils-1.7.8.dist-info/RECORD
