Metadata-Version: 2.1
Name: pyXhUtils
Version: 1.7.8
Summary: A collection of self dev py library
Author-email: xethhung <pypi@xethh.dev>
Project-URL: Homepage, https://github.com/xh-dev-py/xhUtils
Project-URL: Bug Tracker, https://github.com/xh-dev-py/xhUtils/issues
Classifier: Programming Language :: Python :: 3
Classifier: License :: OSI Approved :: MIT License
Classifier: Operating System :: OS Independent
Requires-Python: >=3.6
License-File: LICENSE.txt
Requires-Dist: tzdata
